rsolver/__init__.py
rsolver/asnbuilder.py
rsolver/helper.py
rsolver/parser.py
rsolver/rsabuilder.py
rsolver/rsolver.py
rsolver/gui/rsolver
rsolver/scripts/__init__.py
rsolver/scripts/blind.py
rsolver/scripts/boneh_durfee
rsolver/scripts/boneh_durfee.py
rsolver/scripts/ces1.py
rsolver/scripts/common_modulus.py
rsolver/scripts/common_prime.py
rsolver/scripts/factordb.py
rsolver/scripts/getpqefromdpdqqinv.py
rsolver/scripts/hastad.py
rsolver/scripts/hastadwithouthE.py
rsolver/scripts/lowq.py
rsolver/scripts/multin.py
rsolver/scripts/n_is_prime.py
rsolver/scripts/pyqdadod.py
rsolver/scripts/tokyo.py
rsolver/scripts/wiener.py
rsolver/scripts/wiener2.py
rsolver/scripts/wiener3.py
rsolver/scripts/withdp.py
rsolver/scripts/yafu
rsolver/scripts/zfermat.py
rsolver/scripts/zmultiprimeYafu.py
rsolver-0.1.0.data/scripts/rsolver
rsolver-0.1.0.dist-info/DESCRIPTION.rst
rsolver-0.1.0.dist-info/METADATA
rsolver-0.1.0.dist-info/RECORD
rsolver-0.1.0.dist-info/WHEEL
rsolver-0.1.0.dist-info/metadata.json
rsolver-0.1.0.dist-info/top_level.txt
